erpy/__init__.py
term/__init__.py
term/atom.py
term/basetypes.py
term/bitstring.py
term/codec.py
term/fun.py
term/list.py
term/pid.py
term/py_codec_impl.py
term/reference.py
term/util.py
erpy-0.1.1.dist-info/LICENSE
erpy-0.1.1.dist-info/METADATA
erpy-0.1.1.dist-info/WHEEL
erpy-0.1.1.dist-info/top_level.txt
erpy-0.1.1.dist-info/RECORD
