Metadata-Version: 2.1
Name: erpy
Version: 0.1.1
Summary: Leverages the existing Term package to implement a simple Erlang port driver that communicates over standard input and output.
Author-email: Liam Strand <strandliam@gmail.com>
Project-URL: Homepage, https://github.com/liam-strand/erpy
Project-URL: Issues, https://github.com/liam-strand/erpy/issues
Project-URL: Repository, https://github.com/liam-strand/erpy
Classifier: Programming Language :: Python :: 3
Classifier: License :: OSI Approved :: MIT License
Classifier: Operating System :: OS Independent
Requires-Python: >=3.10
License-File: LICENSE
